flask_data_validation/__init__.py
flask_data_validation/controllers/__init__.py
flask_data_validation/controllers/error_handler.py
flask_data_validation/controllers/validator.py
flask_data_validation/decorators/__init__.py
flask_data_validation/decorators/validation_decorator.py
flask_data_validation/models/__init__.py
flask_data_validation/models/fields.py
flask_data_validation/models/schema.py
flask_validators/__init__.py
flask_validators/controllers/__init__.py
flask_validators/controllers/error_handler.py
flask_validators/controllers/validator.py
flask_validators/decorators/__init__.py
flask_validators/decorators/validation_decorator.py
flask_validators/models/__init__.py
flask_validators/models/fields.py
flask_validators/models/schema.py
flask_validators/models/validate_db.py
flask_validators/models/validate_llm.py
tests/__init__.py
tests/test_flask.py
tests/test_schemas.py
tests/test_validations.py
flask_validators-1.0.dist-info/METADATA
flask_validators-1.0.dist-info/WHEEL
flask_validators-1.0.dist-info/top_level.txt
flask_validators-1.0.dist-info/RECORD
