Metadata-Version: 2.1
Name: flask-validators
Version: 1.0
Summary: Flask request validation
Author: Dimitri Zhorzholiani
Author-email: zhorzholiani.dimitri@gmail.com
Classifier: Programming Language :: Python :: 3
Classifier: Programming Language :: Python :: 3.9
Classifier: License :: OSI Approved :: MIT License
Requires-Python: >=3.6
Requires-Dist: flask
Requires-Dist: SQLAlchemy
Requires-Dist: langid
